analytical/__init__.py
analytical/models.py
analytical/tasks.py
analytical/utils.py
analytical/providers/__init__.py
analytical/providers/base.py
analytical/providers/googleanalytics.py
analytical/vendor/__init__.py
analytical/vendor/ipaddress.py
analytical-0.0.1.dist-info/LICENSE
analytical-0.0.1.dist-info/METADATA
analytical-0.0.1.dist-info/WHEEL
analytical-0.0.1.dist-info/top_level.txt
analytical-0.0.1.dist-info/RECORD
